[{"player":"12345eos1111","stake_amount":"8000000000","dividend_amount":32},{"player":"zhoutingzhen","stake_amount":"7000000000","dividend_amount":28},{"player":"eos223432344","stake_amount":"4695220000","dividend_amount":19},{"player":"g4ydcmzqg4ge","stake_amount":3209420000,"dividend_amount":13},{"player":"gu2tkmrwgyge","stake_amount":2756760000,"dividend_amount":11},{"player":"eos123422343","stake_amount":1987960000,"dividend_amount":8},{"player":"funkmuffin11","stake_amount":439660000,"dividend_amount":1},{"player":"kimsandstrom","stake_amount":429950000,"dividend_amount":1},{"player":"dailyaccount","stake_amount":421140000,"dividend_amount":1},{"player":"refriedqrrrr","stake_amount":403607505,"dividend_amount":1},{"player":"dilbertabaaa","stake_amount":247005000,"dividend_amount":1}]