[{"stake_amount":20740800000,"dividend_amount":47189,"club_id":20},{"stake_amount":3592680000,"dividend_amount":4904,"club_id":12},{"stake_amount":2756760000,"dividend_amount":2509,"club_id":73},{"stake_amount":732487505,"dividend_amount":325,"club_id":23},{"stake_amount":565985000,"dividend_amount":248,"club_id":64},{"stake_amount":450360000,"dividend_amount":204,"club_id":75},{"stake_amount":437010000,"dividend_amount":190,"club_id":44},{"stake_amount":437785000,"dividend_amount":189,"club_id":30},{"stake_amount":346360000,"dividend_amount":152,"club_id":105},{"stake_amount":320055000,"dividend_amount":139,"club_id":58}]