[{"stake_amount":11233240000,"dividend_amount":196403,"club_id":20},{"stake_amount":3903010000,"dividend_amount":40944,"club_id":99},{"stake_amount":3185140000,"dividend_amount":22276,"club_id":61},{"stake_amount":1507560000,"dividend_amount":5271,"club_id":12},{"stake_amount":1000000000,"dividend_amount":3496,"club_id":13},{"stake_amount":713197505,"dividend_amount":2487,"club_id":23},{"stake_amount":552885000,"dividend_amount":1923,"club_id":64},{"stake_amount":449610000,"dividend_amount":1564,"club_id":44},{"stake_amount":423765000,"dividend_amount":1474,"club_id":30},{"stake_amount":338880000,"dividend_amount":1179,"club_id":105}]