[{"stake_amount":21272520000,"dividend_amount":8685,"club_id":20},{"stake_amount":3629370000,"dividend_amount":888,"club_id":12},{"stake_amount":2756760000,"dividend_amount":450,"club_id":73},{"stake_amount":722347505,"dividend_amount":53,"club_id":23},{"stake_amount":542635000,"dividend_amount":37,"club_id":64},{"stake_amount":450360000,"dividend_amount":36,"club_id":75},{"stake_amount":401530000,"dividend_amount":28,"club_id":44},{"stake_amount":350005000,"dividend_amount":25,"club_id":30},{"stake_amount":313260000,"dividend_amount":24,"club_id":105},{"stake_amount":296875000,"dividend_amount":20,"club_id":58}]